README.md
setup.py
bacula_stats/__init__.py
bacula_stats/_version.py
bacula_stats/bacula_stats.py
bacula_stats/functions.py
bacula_stats/views.py
bacula_stats.egg-info/PKG-INFO
bacula_stats.egg-info/SOURCES.txt
bacula_stats.egg-info/dependency_links.txt
bacula_stats.egg-info/entry_points.txt
bacula_stats.egg-info/requires.txt
bacula_stats.egg-info/top_level.txt