Metadata-Version: 1.0
Name: bacula-stats
Version: 0.1.3
Summary: CLI tool to display recent or all bacula backups in table blocks.
Home-page: https://github.com/eayin2/bacula_stats
Author: eayin2
Author-email: eayin2@gmail.com
License: UNKNOWN
Platform: UNKNOWN
